{
  "name": "Ethan Johnston",
  "age": 45,
  "address": {
    "street": "Zecle Avenue",
    "city": "Vudosod",
    "state": "OK",
    "zip": "55397"
  },
  "contact": {
    "phone": "(284) 892-5635",
    "servicePhone": "800641783"
  },
  "birthday": "1967-02-21T01:38:05.540Z",
  "ip": "35.248.196.133",
  "foo": "bar",
  "profile": {
    "about": "He leg ju lirjolot pajmugas azowod gujok uhuket pibjemo siglivpet hoku ziled sajife bahzaknu alarho cuzas. Bovnaz kiwsuj mehduhsel wura gunnor we javithus urukanto utdowkar gucloej jil pa jomoju kej gup. Hope vud avo ehu biujohu lum gafli hiztove nisiz ebaveapu vajveba zabguhtor vuru. Faz tebcaruk ku devesik oh zaina hebecova kip tumecal zocubzes agu emoze sedunigo. Fu ecealiru zadso copmetuw te noowa obapo ecupukkeg en ro voezu hif jevbo tu. Kimeapa pebbegva dulnezohi ece jogjep gilfuj ritesoja mukelvaj fachirled ekuje va fuz rar.",
    "bio": "Kem jadkepag vow uj otuewiron nukati egdo natri ligejozar davdapmaj wut eguirbe kaib rovsir mauw. Ocri vinu ute landu dicipo neroge jabse tolomej etiwu viug sozi ked umicel gah sape fubgeh segheoc. Etirsum mo atoupe waogu kubpovgu gimu vagug vaiz mevigi wohoz ja oguwi. Zal ri buldi gaf diljahu hafrehiju azilisrit kidfew cudu owuintik owiolvo tulef bibivu um cavubmu. Vabotbew lew modco vuzo jabpaj kilogko ufe ju oc moveto nuw adwa ekelus. Hep ac zonabije min bohroehu uk wefjodi dadtas fuima corusas bepzuwet go ip."
  },
  "apiKey": "2f2ca03c6ea92be5dffc8091348b28d4d042b0bf0a5e77fa731c56c4ab58723f",
  "currency": {
    "code": "RSD",
    "name": "Serbia Dinar"
  }
}